odoo/addons/account_payment_multi_deduction/README.rst
odoo/addons/account_payment_multi_deduction/__init__.py
odoo/addons/account_payment_multi_deduction/__manifest__.py
odoo/addons/account_payment_multi_deduction/i18n/account_payment_multi_deduction.pot
odoo/addons/account_payment_multi_deduction/models/__init__.py
odoo/addons/account_payment_multi_deduction/models/account_payment.py
odoo/addons/account_payment_multi_deduction/readme/CONTRIBUTORS.rst
odoo/addons/account_payment_multi_deduction/readme/DESCRIPTION.rst
odoo/addons/account_payment_multi_deduction/readme/HISTORY.rst
odoo/addons/account_payment_multi_deduction/readme/USAGE.rst
odoo/addons/account_payment_multi_deduction/security/ir.model.access.csv
odoo/addons/account_payment_multi_deduction/static/description/icon.png
odoo/addons/account_payment_multi_deduction/static/description/index.html
odoo/addons/account_payment_multi_deduction/tests/__init__.py
odoo/addons/account_payment_multi_deduction/tests/test_payment_multi_deduction.py
odoo/addons/account_payment_multi_deduction/wizard/__init__.py
odoo/addons/account_payment_multi_deduction/wizard/account_payment_deduction.py
odoo/addons/account_payment_multi_deduction/wizard/account_payment_register.py
odoo/addons/account_payment_multi_deduction/wizard/account_payment_register_views.xml
odoo14_addon_account_payment_multi_deduction-14.0.1.1.0.dist-info/METADATA
odoo14_addon_account_payment_multi_deduction-14.0.1.1.0.dist-info/WHEEL
odoo14_addon_account_payment_multi_deduction-14.0.1.1.0.dist-info/top_level.txt
odoo14_addon_account_payment_multi_deduction-14.0.1.1.0.dist-info/RECORD
